{
  "project_info": {
    "project_number": "182725939498",
    "project_id": "canteenapp-417ba",
    "storage_bucket": "canteenapp-417ba.appspot.com"
  },
  "client": [
    {
      "client_info": {
        "mobilesdk_app_id": "1:182725939498:android:fc8e471b7ef51e9ced0e53",
        "android_client_info": {
          "package_name": "com.example.canteenapp"
        }
      },
      "oauth_client": [
        {
          "client_id": "182725939498-0bkhmvlpmns3vqptiqs3os5q12v1lr4e.apps.googleusercontent.com",
          "client_type": 3
        }
      ],
      "api_key": [
        {
          "current_key": "AIzaSyD4AbPABjCx5MULD0baeUsL2Dkk2G-KWTc"
        }
      ],
      "services": {
        "appinvite_service": {
          "other_platform_oauth_client": [
            {
              "client_id": "182725939498-0bkhmvlpmns3vqptiqs3os5q12v1lr4e.apps.googleusercontent.com",
              "client_type": 3
            }
          ]
        }
      }
    }
  ],
  "configuration_version": "1"
}